qoi_rs/__init__.py
qoi_rs/_qoi.abi3.so
qoi_rs/py.typed
qoi_rs/types.py
qoi_rs-4.0.3.dist-info/METADATA
qoi_rs-4.0.3.dist-info/WHEEL
qoi_rs-4.0.3.dist-info/licenses/LICENSE
qoi_rs-4.0.3.dist-info/RECORD
