Metadata-Version: 2.4
Name: qoi-rs
Version: 4.0.3
Classifier: Development Status :: 5 - Production/Stable
Classifier: Intended Audience :: Developers
Classifier: License :: OSI Approved :: Apache Software License
Classifier: Operating System :: OS Independent
Classifier: Programming Language :: Rust
Classifier: Topic :: Software Development
Classifier: Topic :: Software Development :: Libraries
Classifier: Typing :: Typed
Requires-Dist: pillow>=12.0 ; extra == 'pillow'
Provides-Extra: pillow
License-File: LICENSE
License-File: LICENSE
Summary: Blazingly fast library for decoding and encoding QOI images
Keywords: qoi,image,rust
Requires-Python: >=3.12
Project-URL: Source Code, https://codeberg.org/Joshix/qoi-rs-python/
